ollama_flow/__init__.py
ollama_flow/client.py
ollama_flow/models.py
ollama_flow/schemas.py
ollama_flow-0.1.0.dist-info/METADATA
ollama_flow-0.1.0.dist-info/WHEEL
ollama_flow-0.1.0.dist-info/RECORD
