Metadata-Version: 2.4
Name: ollama-flow
Version: 0.1.0
Summary: A Python library for the Ollama API.
Project-URL: Homepage, https://github.com/your-username/ollama-flow
Project-URL: Documentation, https://github.com/your-username/ollama-flow#readme
Project-URL: Repository, https://github.com/your-username/ollama-flow.git
Project-URL: Issues, https://github.com/your-username/ollama-flow/issues
Author-email: Warren <warren@example.com>
License: MIT
Keywords: ai,api,chat,embed,generate,llm,ollama
Classifier: Development Status :: 4 - Beta
Classifier: Intended Audience :: Developers
Classifier: License :: OSI Approved :: MIT License
Classifier: Programming Language :: Python :: 3
Classifier: Programming Language :: Python :: 3.8
Classifier: Programming Language :: Python :: 3.9
Classifier: Programming Language :: Python :: 3.10
Classifier: Programming Language :: Python :: 3.11
Classifier: Programming Language :: Python :: 3.12
Classifier: Topic :: Scientific/Engineering :: Artificial Intelligence
Classifier: Topic :: Software Development :: Libraries :: Python Modules
Requires-Python: >=3.12
Requires-Dist: pydantic>=2.0.0
Requires-Dist: requests>=2.25.0
